matiss/__init__.py
matiss/__version__.py
matiss/distance.py
matiss/gemstone.py
matiss/itol.py
matiss/kraken.py
matiss/mummer.py
matiss/plots.py
matiss/report.py
matiss/stats.py
matiss/strainge.py
matiss/terra.py
matiss/vcf.py
matiss/assets/style.css
matiss-1.0.0.dist-info/licenses/LICENSE
matiss-1.0.0.dist-info/WHEEL
matiss-1.0.0.dist-info/METADATA
matiss-1.0.0.dist-info/RECORD
